Simple_RISC_CPU/Simple_RISC_CPU.srcs/sources_1/new/memory.v
`timescale 1ns / 1ps
//////////////////////////////////////////////////////////////////////////////////
// Company: 
// Engineer: 
// 
// Create Date: 04/13/2025 04:57:33 PM
// Design Name: 
// Module Name: memory
// Project Name: 
// Target Devices: 
// Tool Versions: 
// Description: 
// 
// Dependencies: 
// 
// Revision:
// Revision 0.01 - File Created
// Additional Comments:
// 
//////////////////////////////////////////////////////////////////////////////////


// =============================================================
// Module: Memory
// Function: Store programs (commands) and data.
// Number of memory cells: 32 (5-bit address)
// Data Per Cell: 8-bit
// There are control signals: rd (read), wr (write)
// WARNING: Reading and writing are not allowed at the same time.
// =============================================================
module memory (
    input clk,              // Clock signal
    input rst,              // Synchronous reset, active high
    input rd,               // Read enable, active high
    input wr,               // Write enable, active high
    input [4:0] addr,       // 5-bit address
    inout [7:0] data        // 8-bit bidirectional data port
);

    // Memory array: 32 locations (2^5), each 8 bits wide
    reg [7:0] mem [0:31];
    
    // Internal data output register for read operations
    reg [7:0] data_out;
    
    // Bidirectional data port control
    assign data = (rd && !wr) ? data_out : 8'bz;
    integer i;
    // Memory operations on rising edge of clk
    always @(posedge clk) begin
        if (rst) begin
            // Reset memory (optional, can be modified based on requirements)
            
            for (i = 0; i < 32; i = i + 1) begin
                mem[i] <= 8'b0;
            end
        end else begin
            // Write operation
            if (wr && !rd) begin
                mem[addr] <= data;
            end
            // Read operation
            if (rd && !wr) begin
                data_out <= mem[addr];
            end
        end
    end

endmodule

Simple_RISC_CPU/Simple_RISC_CPU.srcs/sim_1/new/memory_tb.v
module memory_tb;

    // Inputs
    reg clk;
    reg rst;
    reg rd;
    reg wr;
    reg [4:0] addr;
    reg [7:0] data_in;
    
    // Bidirectional data port
    wire [7:0] data;
    
    // Drive bidirectional data port
    assign data = (wr && !rd) ? data_in : 8'bz;
    
    // Instantiate the Memory module
    memory uut (
        .clk(clk),
        .rst(rst),
        .rd(rd),
        .wr(wr),
        .addr(addr),
        .data(data)
    );
    
    // Clock generation
    initial begin
        clk = 0;
        forever #5 clk = ~clk; // 10ns clock period
    end
    
    // Test procedure
    initial begin
        // Initialize inputs
        rst = 0;
        rd = 0;
        wr = 0;
        addr = 5'b0;
        data_in = 8'b0;
        
        // Open VCD file for waveform viewing
        $dumpfile("memory_tb.vcd");
        $dumpvars(0, memory_tb);
        
        // Display header
        $display("Time\tRST\tRD\tWR\tAddr\tData_In\tData_Out");
        $monitor("%0t\t%b\t%b\t%b\t%h\t%h\t%h", $time, rst, rd, wr, addr, data_in, data);
        
        // Test case 1: Reset memory
        #10 rst = 1;
        #10 rst = 0;
        
        // Test case 2: Write to address 0x00
        #10 wr = 1; rd = 0; addr = 5'h00; data_in = 8'hA5;
        #10 wr = 0;
        
        // Test case 3: Read from address 0x00
        #10 rd = 1; wr = 0; addr = 5'h00;
        #10 rd = 0;
        
        // Test case 4: Write to address 0x1F (max address)
        #10 wr = 1; rd = 0; addr = 5'h1F; data_in = 8'hFF;
        #10 wr = 0;
        
        // Test case 5: Read from address 0x1F
        #10 rd = 1; wr = 0; addr = 5'h1F;
        #10 rd = 0;
        
        // Test case 6: Attempt simultaneous read and write (invalid)
        #10 rd = 1; wr = 1; addr = 5'h10; data_in = 8'h55;
        #10 rd = 0; wr = 0;
        
        // Test case 7: Write and read from middle address 0x10
        #10 wr = 1; rd = 0; addr = 5'h10; data_in = 8'h3C;
        #10 wr = 0;
        #10 rd = 1; wr = 0; addr = 5'h10;
        #10 rd = 0;
        
        // Test case 8: Reset and read from address 0x00
        #10 rst = 1;
        #10 rst = 0;
        #10 rd = 1; wr = 0; addr = 5'h00;
        #10 rd = 0;
        
        // Finish simulation
        #10 $display("Test completed");
        $finish;
    end

endmodule

Simple_RISC_CPU/Simple_RISC_CPU.sim/sim_1/behav/xsim/memory_tb.vcd
$date
   Mon May  5 00:52:07 2025
$end

$version
  2024.2.0
  $dumpfile ("memory_tb.vcd") 
$end

$timescale
  1ps
$end

$scope module memory_tb $end
$var reg 1 ! clk $end
$var reg 1 " rst $end
$var reg 1 # rd $end
$var reg 1 $ wr $end
$var reg 5 % addr [4:0] $end
$var reg 8 & data_in [7:0] $end
$var wire 8 ' data [7:0] $end
$scope module uut $end
$var wire 1 ( clk $end
$var wire 1 ) rst $end
$var wire 1 * rd $end
$var wire 1 + wr $end
$var wire 5 , addr [4:0] $end
$var wire 8 ' data [7:0] $end
$var reg 8 - data_out [7:0] $end
$var integer 32 . i [31:0] $end
$upscope $end
$upscope $end
$enddefinitions $end

#0
$dumpvars
0!
0"
0#
0$
b0 %
b0 &
bz '
0(
0)
0*
0+
b0 ,
bx -
bx .
$end

#5000
1!
1(

#10000
0!
1"
0(
1)

#15000
1!
1(

#20000
0!
0"
0(
0)

#25000
1!
1(

#30000
0!
1$
b10100101 &
b10100101 '
0(
1+

#35000
1!
1(

#40000
0!
0$
bz '
0(
0+

#45000
1!
1(

#50000
0!
1#
bx '
0(
1*

#55000
1!
b10100101 '
1(
b10100101 -

#60000
0!
0#
bz '
0(
0*

#65000
1!
1(

#70000
0!
1$
b11111 %
b11111111 &
b11111111 '
0(
1+
b11111 ,

#75000
1!
1(

#80000
0!
0$
bz '
0(
0+

#85000
1!
1(

#90000
0!
1#
b10100101 '
0(
1*

#95000
1!
b11111111 '
1(
b11111111 -

#100000
0!
0#
bz '
0(
0*

#105000
1!
1(

#110000
0!
1#
1$
b10000 %
b1010101 &
0(
1*
1+
b10000 ,

#115000
1!
1(

#120000
0!
0#
0$
0(
0*
0+

#125000
1!
1(

#130000
0!
1$
b111100 &
b111100 '
0(
1+

#135000
1!
1(

#140000
0!
0$
bz '
0(
0+

#145000
1!
1(

#150000
0!
1#
b11111111 '
0(
1*

#155000
1!
b111100 '
1(
b111100 -

#160000
0!
0#
bz '
0(
0*

#165000
1!
1(

#170000
0!
1"
0(
1)

#175000
1!
1(

#180000
0!
0"
0(
0)

#185000
1!
1(

#190000
0!
1#
b0 %
b111100 '
0(
1*
b0 ,

#195000
1!
b0 '
1(
b0 -

#200000
0!
0#
bz '
0(
0*

